predicthq/__init__.py
predicthq/client.py
predicthq/config.py
predicthq/exceptions.py
predicthq/version.py
predicthq/endpoints/__init__.py
predicthq/endpoints/base.py
predicthq/endpoints/decorators.py
predicthq/endpoints/schemas.py
predicthq/endpoints/oauth2/__init__.py
predicthq/endpoints/oauth2/decorators.py
predicthq/endpoints/oauth2/endpoint.py
predicthq/endpoints/oauth2/schemas.py
predicthq/endpoints/v1/__init__.py
predicthq/endpoints/v1/accounts/__init__.py
predicthq/endpoints/v1/accounts/endpoint.py
predicthq/endpoints/v1/accounts/schemas.py
predicthq/endpoints/v1/beam/__init__.py
predicthq/endpoints/v1/beam/endpoint.py
predicthq/endpoints/v1/beam/schemas.py
predicthq/endpoints/v1/broadcasts/__init__.py
predicthq/endpoints/v1/broadcasts/endpoint.py
predicthq/endpoints/v1/broadcasts/schemas.py
predicthq/endpoints/v1/events/__init__.py
predicthq/endpoints/v1/events/endpoint.py
predicthq/endpoints/v1/events/schemas.py
predicthq/endpoints/v1/features/__init__.py
predicthq/endpoints/v1/features/endpoint.py
predicthq/endpoints/v1/features/schemas.py
predicthq/endpoints/v1/places/__init__.py
predicthq/endpoints/v1/places/endpoint.py
predicthq/endpoints/v1/places/schemas.py
predicthq/endpoints/v1/radius/__init__.py
predicthq/endpoints/v1/radius/endpoint.py
predicthq/endpoints/v1/radius/schemas.py
predicthq/endpoints/v1/saved_locations/__init__.py
predicthq/endpoints/v1/saved_locations/endpoint.py
predicthq/endpoints/v1/saved_locations/schemas.py
predicthq-5.2.3.dist-info/licenses/LICENSE
predicthq-5.2.3.dist-info/METADATA
predicthq-5.2.3.dist-info/WHEEL
predicthq-5.2.3.dist-info/top_level.txt
predicthq-5.2.3.dist-info/RECORD
