Metadata-Version: 2.4
Name: predicthq
Version: 5.2.3
Summary: PredictHQ Demand Intelligence
Home-page: https://github.com/predicthq/sdk-py
Author: PredictHQ
Author-email: developers@predicthq.com
License: MIT
Classifier: Development Status :: 4 - Beta
Classifier: Intended Audience :: Developers
Classifier: License :: OSI Approved :: MIT License
Classifier: Environment :: Web Environment
Classifier: Operating System :: OS Independent
Classifier: Programming Language :: Python
Classifier: Programming Language :: Python :: 3
Classifier: Programming Language :: Python :: 3.8
Classifier: Programming Language :: Python :: 3.9
Classifier: Programming Language :: Python :: 3.10
Classifier: Programming Language :: Python :: 3.11
Classifier: Programming Language :: Python :: 3.12
Classifier: Topic :: Software Development :: Libraries :: Python Modules
Requires-Python: >=3.8
License-File: LICENSE
Requires-Dist: pydantic<3,>=2
Requires-Dist: requests>=2.7.0
Requires-Dist: python-dateutil>=2.4.2
Requires-Dist: pytz<=2023.3,>=2017.2
Requires-Dist: stamina<25,>=24.3.0
Requires-Dist: deprecated<2.0,>=1.2.18
Dynamic: author
Dynamic: author-email
Dynamic: classifier
Dynamic: description
Dynamic: description-content-type
Dynamic: home-page
Dynamic: license
Dynamic: license-file
Dynamic: requires-dist
Dynamic: requires-python
Dynamic: summary
